pyrdai/__init__.py
pyrdai/nlp.py
pyrdai/ocr.py
pyrdai-1.0.2.dist-info/LICENSE
pyrdai-1.0.2.dist-info/METADATA
pyrdai-1.0.2.dist-info/WHEEL
pyrdai-1.0.2.dist-info/top_level.txt
pyrdai-1.0.2.dist-info/RECORD
