Metadata-Version: 2.1
Name: pyrdai
Version: 1.0.2
Summary: reshape data AI Services in py language 
Home-page: http://www.reshapedata.com
Author: Reshapedata
Author-email: hulilei@takewiki.com.cn
License: Apache License
Keywords: reshapedata,rdai,pyrdai
Platform: UNKNOWN
Requires-Python: >=3.6
Requires-Dist: pymssql
